{
    "experiences": [
        {
            "title": "Bachelors of Technology",
            "subtitle": "Vellore Institute of Technology",
            "workType": "Computer Science and Engineering",
            "workDescription": [
               "Score - 87%"
            ],
            "dateText": "2020 – Present"
        },
        {
            "title": "Intermediate",
            "subtitle": "Atomic Energy Central School No.3",
            "workType": "PCM-Computer Science",
            "workDescription": [
                "Score - 92.6%"
            ],
            "dateText": "2018 – 2020"
        },
        {
            "title": "High- School",
            "subtitle": "Atomic Energy Central School No.1",
            "workType": "PCMB",
            "workDescription": [
                "Score - 91.2%"
            ],
            "dateText": "2018"
        }
    ]
}